google_weather_tools-0.3.2.data/scripts/download-status
google_weather_tools-0.3.2.data/scripts/weather-dl
google_weather_tools-0.3.2.data/scripts/weather-mv
google_weather_tools-0.3.2.data/scripts/weather-sp
weather_dl/__init__.py
weather_dl/download_status.py
weather_dl/download_status_test.py
weather_dl/setup.py
weather_dl/download_pipeline/__init__.py
weather_dl/download_pipeline/clients.py
weather_dl/download_pipeline/clients_test.py
weather_dl/download_pipeline/config.py
weather_dl/download_pipeline/config_test.py
weather_dl/download_pipeline/fetcher.py
weather_dl/download_pipeline/fetcher_test.py
weather_dl/download_pipeline/manifest.py
weather_dl/download_pipeline/manifest_test.py
weather_dl/download_pipeline/parsers.py
weather_dl/download_pipeline/parsers_test.py
weather_dl/download_pipeline/partition.py
weather_dl/download_pipeline/partition_test.py
weather_dl/download_pipeline/pipeline.py
weather_dl/download_pipeline/pipeline_test.py
weather_dl/download_pipeline/stores.py
weather_dl/download_pipeline/stores_test.py
weather_dl/download_pipeline/util.py
weather_mv/__init__.py
weather_mv/setup.py
weather_mv/loader_pipeline/__init__.py
weather_mv/loader_pipeline/bq.py
weather_mv/loader_pipeline/bq_test.py
weather_mv/loader_pipeline/execution_test.py
weather_mv/loader_pipeline/pipeline.py
weather_mv/loader_pipeline/pipeline_test.py
weather_mv/loader_pipeline/sinks.py
weather_mv/loader_pipeline/sinks_test.py
weather_mv/loader_pipeline/streaming.py
weather_mv/loader_pipeline/streaming_test.py
weather_mv/loader_pipeline/util.py
weather_mv/loader_pipeline/util_test.py
weather_sp/__init__.py
weather_sp/setup.py
weather_sp/splitter_pipeline/__init__.py
weather_sp/splitter_pipeline/file_name_utils.py
weather_sp/splitter_pipeline/file_name_utils_test.py
weather_sp/splitter_pipeline/file_splitters.py
weather_sp/splitter_pipeline/file_splitters_test.py
weather_sp/splitter_pipeline/pipeline.py
weather_sp/splitter_pipeline/pipeline_test.py
google_weather_tools-0.3.2.dist-info/LICENSE
google_weather_tools-0.3.2.dist-info/METADATA
google_weather_tools-0.3.2.dist-info/WHEEL
google_weather_tools-0.3.2.dist-info/top_level.txt
google_weather_tools-0.3.2.dist-info/RECORD
