Metadata-Version: 2.1
Name: google-weather-tools
Version: 0.3.2
Summary: Apache Beam pipelines to make weather data accessible and useful.
Home-page: https://weather-tools.readthedocs.io/
Author: Anthromets
Author-email: anthromets-ecmwf@google.com
License: License :: OSI Approved :: Apache Software License
Project-URL: Issue Tracking, http://github.com/google/weather-tools/issues
Platform: darwin
Platform: linux
Classifier: Development Status :: 4 - Beta
Classifier: Environment :: Console
Classifier: Intended Audience :: Science/Research
Classifier: Intended Audience :: Developers
Classifier: Intended Audience :: Information Technology
Classifier: License :: OSI Approved :: Apache Software License
Classifier: Operating System :: MacOS :: MacOS X
Classifier: Operating System :: POSIX
Classifier: Programming Language :: Python :: 3.7
Classifier: Programming Language :: Python :: 3.8
Classifier: Topic :: Scientific/Engineering :: Atmospheric Science
Requires-Python: >=3.7, <3.9
License-File: LICENSE
Requires-Dist: apache-beam[gcp]
Provides-Extra: dev
Requires-Dist: tox ; extra == 'dev'
Requires-Dist: sphinx (>=2.1) ; extra == 'dev'
Requires-Dist: myst-parser ; extra == 'dev'
Requires-Dist: cdsapi ; extra == 'dev'
Requires-Dist: ecmwf-api-client ; extra == 'dev'
Requires-Dist: apache-beam[gcp] ; extra == 'dev'
Requires-Dist: numpy (>=1.19.1) ; extra == 'dev'
Requires-Dist: pandas ; extra == 'dev'
Requires-Dist: xarray ; extra == 'dev'
Requires-Dist: requests (>=2.24.0) ; extra == 'dev'
Requires-Dist: firebase-admin (>=5.0.0) ; extra == 'dev'
Requires-Dist: google-cloud-datastore (<2,>=1.15.0) ; extra == 'dev'
Requires-Dist: google-cloud-firestore ; extra == 'dev'
Requires-Dist: urllib3 (==1.25.11) ; extra == 'dev'
Requires-Dist: pyparsing (==2.4.2) ; extra == 'dev'
Requires-Dist: dataclasses ; extra == 'dev'
Requires-Dist: numpy ; extra == 'dev'
Requires-Dist: google-cloud-bigquery ; extra == 'dev'
Requires-Dist: google-cloud-storage (==2.2.1) ; extra == 'dev'
Requires-Dist: cfgrib ; extra == 'dev'
Requires-Dist: netcdf4 ; extra == 'dev'
Requires-Dist: geojson ; extra == 'dev'
Requires-Dist: rioxarray ; extra == 'dev'
Requires-Dist: numpy (>=1.20.3) ; extra == 'dev'
Requires-Dist: pygrib ; extra == 'dev'
Requires-Dist: scipy ; extra == 'dev'
Requires-Dist: pytype (==2021.11.29) ; extra == 'dev'
Requires-Dist: flake8 ; extra == 'dev'
Requires-Dist: pytest ; extra == 'dev'
Requires-Dist: pytest-subtests ; extra == 'dev'
Requires-Dist: xarray-beam ; extra == 'dev'
Requires-Dist: absl-py ; extra == 'dev'
Provides-Extra: test
Requires-Dist: cdsapi ; extra == 'test'
Requires-Dist: ecmwf-api-client ; extra == 'test'
Requires-Dist: apache-beam[gcp] ; extra == 'test'
Requires-Dist: numpy (>=1.19.1) ; extra == 'test'
Requires-Dist: pandas ; extra == 'test'
Requires-Dist: xarray ; extra == 'test'
Requires-Dist: requests (>=2.24.0) ; extra == 'test'
Requires-Dist: firebase-admin (>=5.0.0) ; extra == 'test'
Requires-Dist: google-cloud-datastore (<2,>=1.15.0) ; extra == 'test'
Requires-Dist: google-cloud-firestore ; extra == 'test'
Requires-Dist: urllib3 (==1.25.11) ; extra == 'test'
Requires-Dist: pyparsing (==2.4.2) ; extra == 'test'
Requires-Dist: dataclasses ; extra == 'test'
Requires-Dist: numpy ; extra == 'test'
Requires-Dist: google-cloud-bigquery ; extra == 'test'
Requires-Dist: google-cloud-storage (==2.2.1) ; extra == 'test'
Requires-Dist: cfgrib ; extra == 'test'
Requires-Dist: netcdf4 ; extra == 'test'
Requires-Dist: geojson ; extra == 'test'
Requires-Dist: rioxarray ; extra == 'test'
Requires-Dist: numpy (>=1.20.3) ; extra == 'test'
Requires-Dist: pygrib ; extra == 'test'
Requires-Dist: scipy ; extra == 'test'
Requires-Dist: pytype (==2021.11.29) ; extra == 'test'
Requires-Dist: flake8 ; extra == 'test'
Requires-Dist: pytest ; extra == 'test'
Requires-Dist: pytest-subtests ; extra == 'test'
Requires-Dist: xarray-beam ; extra == 'test'
Requires-Dist: absl-py ; extra == 'test'
